[
  {
    "followers": 6277637,
    "genre": "j-pop",
    "genres": [
      "j-pop",
      "anime",
      "j-rock"
    ],
    "href": "https://open.spotify.com/artist/4QvgGvpgzgyUOo8Yp8LDm9",
    "id": "4QvgGvpgzgyUOo8Yp8LDm9",
    "image": "https://i.scdn.co/image/ab6761610000e5eb3745f83871d6016e5e9ce5d8",
    "name": "Mrs. GREEN APPLE",
    "top_track": {
      "href": "https://open.spotify.com/track/21VsLvoE7elUmJZLSawaMh",
      "name": "ライラック"
    }
  },
  {
    "followers": 222,
    "genre": "k-pop",
    "genres": [],
    "href": "https://open.spotify.com/artist/0s4JRhiI6djokTbOhqUd7f",
    "id": "0s4JRhiI6djokTbOhqUd7f",
    "image": "https://i.scdn.co/image/ab67616d0000b2738134e797356b04becdec4444",
    "name": "SWAPAN DEBBARMA",
    "top_track": {
      "href": "https://open.spotify.com/track/0hlnibK7prBmuYeUvxw3Wi",
      "name": "Ang Rwchapkhe"
    }
  },
  {
    "followers": 3230002,
    "genre": "jazz",
    "genres": [
      "vocal jazz",
      "jazz blues",
      "soul",
      "soul jazz",
      "jazz",
      "blues"
    ],
    "href": "https://open.spotify.com/artist/7G1GBhoKtEPnP86X2PvEYO",
    "id": "7G1GBhoKtEPnP86X2PvEYO",
    "image": "https://i.scdn.co/image/ab6761610000e5eb136c51c848c26a6cce7f9e56",
    "name": "Nina Simone",
    "top_track": {
      "href": "https://open.spotify.com/track/6Rqn2GFlmvmV4w9Ala0I1e",
      "name": "Feeling Good"
    }
  }
]