[
  {
    "followers": 9678130,
    "genre": "hip hop",
    "genres": [
      "chicago drill",
      "drill"
    ],
    "href": "https://open.spotify.com/artist/3hcs9uc56yIGFCSy9leWe7",
    "id": "3hcs9uc56yIGFCSy9leWe7",
    "image": "https://i.scdn.co/image/ab6761610000e5eb09791422702c3fa9780468d4",
    "name": "Lil Durk",
    "top_track": {
      "href": "https://open.spotify.com/track/2SAqBLGA283SUiwJ3xOUVI",
      "name": "Laugh Now Cry Later (feat. Lil Durk)"
    }
  },
  {
    "followers": 154,
    "genre": "edm",
    "genres": [],
    "href": "https://open.spotify.com/artist/6UFzVzf3ps0jAWqag24aLU",
    "id": "6UFzVzf3ps0jAWqag24aLU",
    "image": "https://i.scdn.co/image/ab67616d0000b273623d5644a416d7b37cb1c2be",
    "name": "Braydon Wollmann",
    "top_track": {
      "href": "https://open.spotify.com/track/6tDO9GQEgpjrmI3Wz6iA9p",
      "name": "She Dances"
    }
  },
  {
    "followers": 7289594,
    "genre": "indie",
    "genres": [
      "baroque pop"
    ],
    "href": "https://open.spotify.com/artist/1moxjboGR7GNWYIMWsRjgG",
    "id": "1moxjboGR7GNWYIMWsRjgG",
    "image": "https://i.scdn.co/image/ab6761610000e5eb836eb0a7a82eb8f4133ee04d",
    "name": "Florence + The Machine",
    "top_track": {
      "href": "https://open.spotify.com/track/1YLJVmuzeM2YSUkCCaTNUB",
      "name": "Dog Days Are Over"
    }
  }
]